vinci_auth/__init__.py
vinci_auth/token_retriever.py
vinci_auth_python_pkg-1.0.5.dist-info/METADATA
vinci_auth_python_pkg-1.0.5.dist-info/WHEEL
vinci_auth_python_pkg-1.0.5.dist-info/top_level.txt
vinci_auth_python_pkg-1.0.5.dist-info/RECORD
