Metadata-Version: 2.1
Name: vinci-auth-python-pkg
Version: 1.0.5
Summary: A simple package to get vinci users auth token
Home-page: http://tfs.util.vinci.net:8080/tfs/DefaultCollection/Vinci.Poc/Vinci.Poc%20Team/_git/vinci-auth-python-pkg
Author: Igor Lisbôa (TI-Sistemas)
Author-email: ti-sistemas@vincipartners.com
Classifier: Programming Language :: Python :: 3
Classifier: License :: OSI Approved :: MIT License
Classifier: Operating System :: OS Independent
